xlocale.cpython-35m-x86_64-linux-gnu.so
xlocale-1.3.4.dist-info/metadata.json
xlocale-1.3.4.dist-info/WHEEL
xlocale-1.3.4.dist-info/RECORD
xlocale-1.3.4.dist-info/DESCRIPTION.rst
xlocale-1.3.4.dist-info/top_level.txt
xlocale-1.3.4.dist-info/METADATA
