Metadata-Version: 2.0
Name: xlocale
Version: 1.3.4
Summary: UNKNOWN
Home-page: https://github.com/wichert/xlocale
Author: Wichert Akkerman
Author-email: wichert@wiggy.net
License: BSD
Keywords: xlocale locale i18n l10n
Platform: UNKNOWN
Classifier: Intended Audience :: Developers
Classifier: License :: DFSG approved
Classifier: License :: OSI Approved :: BSD License
Classifier: Operating System :: OS Independent
Classifier: Programming Language :: Python :: 2
Classifier: Programming Language :: Python :: 2.6
Classifier: Programming Language :: Python :: 2.7
Classifier: Programming Language :: Python :: 3
Classifier: Programming Language :: Python :: 3.4
Classifier: Programming Language :: Python :: 3.5
Classifier: Programming Language :: Python :: 3.6
Classifier: Topic :: Software Development :: Libraries :: Python Modules
